easydown/__init__.py
easydown/main.py
easydown-0.1.3.dist-info/METADATA
easydown-0.1.3.dist-info/WHEEL
easydown-0.1.3.dist-info/top_level.txt
easydown-0.1.3.dist-info/RECORD
